cli/__init__.py
cli/__main__.py
cli/main.py
miot/__init__.py
miot/config.py
miot/log.py
miot/mqtt.py
miot-1.0.42.dist-info/LICENSE
miot-1.0.42.dist-info/METADATA
miot-1.0.42.dist-info/WHEEL
miot-1.0.42.dist-info/entry_points.txt
miot-1.0.42.dist-info/top_level.txt
miot-1.0.42.dist-info/RECORD
