Metadata-Version: 2.1
Name: miot
Version: 1.0.42
Summary: Modular Internet of Things
Home-page: https://github.com/automation-itspeedway-net/miot.git
Author: Si Dunford
Author-email: dunford.sj+miot@gmail.com
License: MIT
Platform: UNKNOWN
Classifier: Development Status :: 2 - Pre-Alpha
Classifier: Programming Language :: Python :: 3
Classifier: License :: OSI Approved :: MIT License
Classifier: Operating System :: OS Independent
Classifier: Intended Audience :: Other Audience
Classifier: Topic :: Scientific/Engineering :: Human Machine Interfaces
Requires-Python: >=3.6
Requires-Dist: paho-mqtt
Requires-Dist: configparser
